django_secure_contact_form/__init__.py
django_secure_contact_form/admin.py
django_secure_contact_form/apps.py
django_secure_contact_form/captcha_utils.py
django_secure_contact_form/forms.py
django_secure_contact_form/models.py
django_secure_contact_form/signals.py
django_secure_contact_form/tests.py
django_secure_contact_form/urls.py
django_secure_contact_form/views.py
django_secure_contact_form/migrations/0001_initial.py
django_secure_contact_form/migrations/0002_contactformsettings.py
django_secure_contact_form/migrations/__init__.py
django_secure_contact_form/templates/django_secure_contact_form/contact_form.html
django_secure_contact_form/templates/django_secure_contact_form/contact_success.html
django_secure_contact_form/templates/django_secure_contact_form/email_template.html
django_secure_contact_form_plugin/__init__.py
django_secure_contact_form_plugin/asgi.py
django_secure_contact_form_plugin/settings.py
django_secure_contact_form_plugin/urls.py
django_secure_contact_form_plugin/wsgi.py
django_secure_contact_form-0.2.1.dist-info/LICENSE
django_secure_contact_form-0.2.1.dist-info/METADATA
django_secure_contact_form-0.2.1.dist-info/WHEEL
django_secure_contact_form-0.2.1.dist-info/top_level.txt
django_secure_contact_form-0.2.1.dist-info/RECORD
