Metadata-Version: 2.1
Name: django-secure-contact-form
Version: 0.2.1
Summary: A secure and customizable contact form for Django projects.
Home-page: https://github.com/Gavin-Humphrey/django-secure-contact-form
Author: Gavin Humphrey
Author-email: gavin.humphrey.pro@gmail.com
License: MIT
Platform: UNKNOWN
Classifier: Environment :: Web Environment
Classifier: Framework :: Django
Classifier: Intended Audience :: Developers
Classifier: License :: OSI Approved :: MIT License
Classifier: Operating System :: OS Independent
Classifier: Programming Language :: Python
Classifier: Programming Language :: Python :: 3
Classifier: Topic :: Internet :: WWW/HTTP
Classifier: Topic :: Internet :: WWW/HTTP :: Dynamic Content
License-File: LICENSE
